casm/__init__.py
casm/api/__init__.py
casm/api/api.py
casm/holoviews/__init__.py
casm/holoviews/plot_prim.py
casm/info/__init__.py
casm/info/info.py
casm/learn/__init__.py
casm/learn/direct_selection.py
casm/learn/evolve.py
casm/learn/feature_selection.py
casm/learn/fit.py
casm/learn/linear_model.py
casm/learn/model_selection.py
casm/learn/selection_wrapper.py
casm/learn/tools.py
casm/misc/__init__.py
casm/misc/compat.py
casm/misc/contexts.py
casm/misc/matrix.py
casm/misc/noindent.py
casm/misc/unbuffered.py
casm/project/__init__.py
casm/project/io.py
casm/project/project.py
casm/project/query.py
casm/project/selection.py
casm/project/structure.py
casm/project/syminfo.py
casm/scripts/__init__.py
casm/scripts/casm.py
casm/scripts/casm_calc.py
casm/scripts/casm_convert.py
casm/scripts/casm_learn.py
casm/scripts/casm_view.py
casm/scripts/vasp_converge.py
casm/scripts/vasp_relax.py
casm/scripts/vasp_relax_report.py
casm/scripts/vasp_setup.py
casm/vasp/__init__.py
casm/vasp/converge.py
casm/vasp/error.py
casm/vasp/neb.py
casm/vasp/relax.py
casm/vasp/run.py
casm/vasp/io/__init__.py
casm/vasp/io/attribute_classes.py
casm/vasp/io/incar.py
casm/vasp/io/io.py
casm/vasp/io/kpoints.py
casm/vasp/io/orbital_occupation.py
casm/vasp/io/oszicar.py
casm/vasp/io/outcar.py
casm/vasp/io/poscar.py
casm/vasp/io/species.py
casm/vasp/io/vaspio.py
casm/vasp/io/vasprun.py
casm/vaspwrapper/__init__.py
casm/vaspwrapper/converge.py
casm/vaspwrapper/relax.py
casm/vaspwrapper/vasp_calculator_base.py
casm/vaspwrapper/vaspwrapper.py
casm/wrapper/__init__.py
casm/wrapper/misc.py
casm_python-1.2.1.data/data/LICENSE
casm_python-1.2.1.dist-info/LICENSE
casm_python-1.2.1.dist-info/METADATA
casm_python-1.2.1.dist-info/WHEEL
casm_python-1.2.1.dist-info/entry_points.txt
casm_python-1.2.1.dist-info/top_level.txt
casm_python-1.2.1.dist-info/RECORD
