Metadata-Version: 2.1
Name: casm-python
Version: 1.2.1
Summary: CASM Python interface, tools, and wrappers.
Home-page: https://github.com/prisms-center/CASMpython
Author: CASM developers
Author-email: casm-developers@lists.engr.ucsb.edu
License: LGPL2.1+
Platform: UNKNOWN
Classifier: Development Status :: 5 - Production/Stable
Classifier: License :: OSI Approved :: GNU Lesser General Public License v2 or later (LGPLv2+)
Classifier: Programming Language :: Python
Classifier: Programming Language :: Python :: 3
Classifier: Topic :: Scientific/Engineering
Requires-Dist: deap
Requires-Dist: mock
Requires-Dist: pandas
Requires-Dist: prisms-jobs
Requires-Dist: scikit-learn
Requires-Dist: scipy
Requires-Dist: sh
